pymbse/client/__init__.py
pymbse/client/cache.py
pymbse/client/config.py
pymbse/client/gui/__init__.py
pymbse/client/manage.py
pymbse/client/model.py
pymbse_client-0.0.3.dist-info/LICENSES/BSD-4-Clause.txt
pymbse_client-0.0.3.dist-info/LICENSES/CC0-1.0.txt
pymbse_client-0.0.3.dist-info/METADATA
pymbse_client-0.0.3.dist-info/WHEEL
pymbse_client-0.0.3.dist-info/RECORD
