Metadata-Version: 2.1
Name: pymbse-client
Version: 0.0.3
Summary: PyMBSE client library
Home-page: https://pymbse.docs.cern.ch
License: MIT
Author: Matthias Bonora
Author-email: matthias.bonora@cern.ch
Requires-Python: >=3.10,<4.0
Classifier: Intended Audience :: Education
Classifier: License :: OSI Approved :: MIT License
Classifier: Operating System :: OS Independent
Classifier: Programming Language :: Python :: 3
Classifier: Programming Language :: Python :: 3.10
Classifier: Programming Language :: Python :: 3.11
Classifier: Programming Language :: Python :: 3.12
Classifier: Programming Language :: Python :: 3.13
Provides-Extra: gui
Requires-Dist: ipyvuetify (>=1.10.0,<2.0.0) ; extra == "gui"
Requires-Dist: matplotlib (>=3.9.2,<4.0.0) ; extra == "gui"
Requires-Dist: networkx (>=3.3,<4.0) ; extra == "gui"
Requires-Dist: pydantic (>=2.8.2,<3.0.0)
Requires-Dist: pydantic-yaml (>=1.3.0,<2.0.0)
Requires-Dist: pymbse-commons (>=0.1.2,<0.2.0)
Requires-Dist: pyyaml (>=6.0.2,<7.0.0)
Requires-Dist: requests-toolbelt (>=1.0.0,<2.0.0)
Requires-Dist: solara (>=1.37.1,<2.0.0) ; extra == "gui"
Requires-Dist: tqdm (>=4.66.5,<5.0.0)
Project-URL: Documentation, https://pymbse.docs.cern.ch/pymbse-client
Project-URL: Repository, https://gitlab.cern.ch/pymbse/pymbse-client
